pepubot/__init__.py
pepubot/__main__.py
pepubot/hashing.py
pepubot/lottery_box.py
pepubot/messages.py
pepubot/runner.py
pepubot/settings.py
pepubot/slack.py
pepubot/storage.py
pepubot/times.py
pepubot/userinfo.py
pepubot/tests/__init__.py
pepubot/tests/test_runner.py
pepubot-0.1.0.dist-info/LICENSE
pepubot-0.1.0.dist-info/METADATA
pepubot-0.1.0.dist-info/WHEEL
pepubot-0.1.0.dist-info/entry_points.txt
pepubot-0.1.0.dist-info/top_level.txt
pepubot-0.1.0.dist-info/RECORD
