Metadata-Version: 2.1
Name: pepubot
Version: 0.1.0
Summary: Friday Bottle Lottery Bot for Slack
Home-page: https://github.com/andersinno/pepubot/
Author: Tuomas Suutari
Author-email: tuomas.suutari@anders.fi
Maintainer: Anders Innovations
Maintainer-email: support@anders.fi
License: MIT
Keywords: pepu,bot,Friday,bottle,lottery,Slack
Platform: any
Classifier: Development Status :: 3 - Alpha
Classifier: Intended Audience :: Developers
Classifier: License :: OSI Approved :: MIT License
Classifier: Natural Language :: English
Classifier: Operating System :: OS Independent
Classifier: Programming Language :: Python
Classifier: Programming Language :: Python :: 3
Classifier: Programming Language :: Python :: 3 :: Only
Classifier: Programming Language :: Python :: 3.7
Classifier: Topic :: Communications :: Chat
Classifier: Typing :: Typed
Requires-Dist: aiofiles
Requires-Dist: python-dateutil
Requires-Dist: pytz
Requires-Dist: slackclient[optional]
